iris/__init__.py
iris/moldata.py
iris/setup.py
iris/spectrum.py
iris_jwst-0.3.1.dist-info/LICENCE
iris_jwst-0.3.1.dist-info/METADATA
iris_jwst-0.3.1.dist-info/WHEEL
iris_jwst-0.3.1.dist-info/top_level.txt
iris_jwst-0.3.1.dist-info/RECORD
