Metadata-Version: 2.1
Name: iris-jwst
Version: 0.3.1
Summary: iris-jwst is a GPU-accelerated package to generate high-resolution opacity-weighted molecular line intensities to model disk spectra.
Author-email: "Carlos E. Romero-Mirza" <carlos.romero_mirza@cfa.harvard.edu>
Project-URL: Homepage, https://github.com/munozcar/IRIS
Classifier: Programming Language :: Python :: 3
Classifier: License :: OSI Approved :: MIT License
Classifier: Operating System :: OS Independent
Requires-Python: >=3.8
License-File: LICENCE
